covvfit/__init__.py
covvfit/_cli/__init__.py
covvfit/_cli/check.py
covvfit/_cli/freyja.py
covvfit/_cli/infer.py
covvfit/_deconvolution.py
covvfit/_dynamics.py
covvfit/_numeric.py
covvfit/_padding.py
covvfit/_preprocess_abundances.py
covvfit/_quasimultinomial.py
covvfit/_random.py
covvfit/_splines.py
covvfit/cli.py
covvfit/plotting/__init__.py
covvfit/plotting/_grid.py
covvfit/plotting/_simplex.py
covvfit/plotting/_timeseries.py
covvfit/simulation/__init__.py
covvfit/simulation/_logistic.py
covvfit/simulation/_sde.py
covvfit-0.3.1.dist-info/LICENSE
covvfit-0.3.1.dist-info/METADATA
covvfit-0.3.1.dist-info/WHEEL
covvfit-0.3.1.dist-info/entry_points.txt
covvfit-0.3.1.dist-info/RECORD
