Metadata-Version: 2.1
Name: covvfit
Version: 0.3.1
Summary: 
Author: David Dreifuss
Author-email: david.dreifuss@bsse.ethz.ch
Requires-Python: >=3.10,<3.12
Classifier: Programming Language :: Python :: 3
Classifier: Programming Language :: Python :: 3.10
Classifier: Programming Language :: Python :: 3.11
Requires-Dist: jax (>=0.4.20,<0.5.0)
Requires-Dist: jaxlib (>=0.4.20,<0.5.0)
Requires-Dist: jaxtyping (>=0.2.36,<0.3.0)
Requires-Dist: matplotlib (>=3.8.0,<4.0.0)
Requires-Dist: numpy (>=1.24.3,<2.0.0)
Requires-Dist: numpyro (>=0.14.0,<0.15.0)
Requires-Dist: pango-aliasor (>=0.3.0,<0.4.0)
Requires-Dist: pydantic (>=2.10.6,<3.0.0)
Requires-Dist: pyyaml (>=6.0.2,<7.0.0)
Requires-Dist: scipy (>=1.11.3,<2.0.0)
Requires-Dist: seaborn (>=0.13.2,<0.14.0)
Requires-Dist: subplots-from-axsize (>=0.1.9,<0.2.0)
Requires-Dist: typer (>=0.15.1,<0.16.0)
